Metadata-Version: 2.1
Name: GammaLab
Version: 0.8.3
Summary: Toolkit for soundcard gamma ray spectroscopy
Home-page: https://github.com/ipelupessy/gammalab
Author: F.I. Pelupessy
License: GPLv3
Classifier: Development Status :: 4 - Beta
Classifier: Intended Audience :: Developers
Classifier: Intended Audience :: Science/Research
Classifier: License :: OSI Approved :: GNU General Public License v3 (GPLv3) 
Classifier: Natural Language :: English
Classifier: Operating System :: OS Independent
Classifier: Programming Language :: Python :: 3.6
Classifier: Programming Language :: Python :: 3.7
Classifier: Programming Language :: Python :: 3.8
Classifier: Programming Language :: Python :: 3.10
Classifier: Topic :: Scientific/Engineering :: Physics
Requires-Python: >=3.6
License-File: LICENSE
